[{"id":101, "title":"Bird sketch book 01", "image":"/images/alipede/bird/bird-01.png"},
 {"id":102, "title":"Bird sketch book 02", "image":"/images/alipede/bird/bird-02.png"},
 {"id":103, "title":"Bird sketch book 03", "image":"/images/alipede/bird/bird-03.png"},
 {"id":104, "title":"Bird sketch book 04", "image":"/images/alipede/bird/bird-04.png"},
 {"id":105, "title":"Bird sketch book 05", "image":"/images/alipede/bird/bird-05.png"},
 {"id":106, "title":"Bird sketch book 06", "image":"/images/alipede/bird/bird-06.png"},
 {"id":107, "title":"Bird sketch book 07", "image":"/images/alipede/bird/bird-07.png"},
 {"id":108, "title":"Bird sketch book 08", "image":"/images/alipede/bird/bird-08.png"},
 {"id":109, "title":"Bird sketch book 09", "image":"/images/alipede/bird/bird-09.png"},
 {"id":110, "title":"Bird sketch book 10", "image":"/images/alipede/bird/bird-10.png"},
 {"id":111, "title":"Bird sketch book 11", "image":"/images/alipede/bird/bird-11.png"},
 {"id":112, "title":"Bird sketch book 12", "image":"/images/alipede/bird/bird-12.png"},
 {"id":113, "title":"Bird sketch book 13", "image":"/images/alipede/bird/bird-13.png"}]